aerosol/__init__.py
aerosol/aerosol_analyzer.py
aerosol/fitting.py
aerosol/functions.py
aerosol/my_cmd.py
aerosol/plotting.py
aerosol_functions-0.1.13.dist-info/LICENSE.txt
aerosol_functions-0.1.13.dist-info/METADATA
aerosol_functions-0.1.13.dist-info/WHEEL
aerosol_functions-0.1.13.dist-info/entry_points.txt
aerosol_functions-0.1.13.dist-info/top_level.txt
aerosol_functions-0.1.13.dist-info/RECORD
