Metadata-Version: 2.1
Name: aerosol-functions
Version: 0.1.13
Summary: Functions to analyze atmospheric aerosol data
Home-page: https://github.com/jlpl/aerosol-functions
Author: Janne Lampilahti
Author-email: janne.lampilahti@helsinki.fi
Requires-Python: >=3.9
License-File: LICENSE.txt
Requires-Dist: pandas>=1.1.0
Requires-Dist: numpy>=1.19.0
Requires-Dist: matplotlib>=3.3.4
Requires-Dist: scipy>=1.5.3
Requires-Dist: bokeh>=3.6.3
Requires-Dist: astral>=3.2
Requires-Dist: kneed>=0.8.5
Requires-Dist: scikit-learn>=1.3.0
